aldryn_translation_tools/__init__.py
aldryn_translation_tools/admin.py
aldryn_translation_tools/models.py
aldryn_translation_tools/sitemaps.py
aldryn_translation_tools/utils.py
aldryn_translation_tools/static/css/admin/all-translations-mixin.css
test_addon/__init__.py
test_addon/cms_apps.py
test_addon/managers.py
test_addon/models.py
test_addon/urls.py
test_addon/views.py
djangocms_aldryn_translation_tools-1.0.2.dist-info/LICENSE.txt
djangocms_aldryn_translation_tools-1.0.2.dist-info/METADATA
djangocms_aldryn_translation_tools-1.0.2.dist-info/WHEEL
djangocms_aldryn_translation_tools-1.0.2.dist-info/top_level.txt
djangocms_aldryn_translation_tools-1.0.2.dist-info/RECORD
