Metadata-Version: 2.1
Name: djangocms-aldryn-translation-tools
Version: 1.0.2
Summary: Collection of helpers and mixins for translated projects.
Home-page: https://github.com/CZ-NIC/djangocms-aldryn-translation-tools
Author: Divio AG
Author-email: info@divio.ch
License: BSD License
Platform: OS Independent
Classifier: Development Status :: 2 - Pre-Alpha
Classifier: Environment :: Web Environment
Classifier: Framework :: Django
Classifier: Intended Audience :: Developers
Classifier: License :: OSI Approved :: BSD License
Classifier: Operating System :: OS Independent
Classifier: Programming Language :: Python
Classifier: Topic :: Internet :: WWW/HTTP :: Dynamic Content
Classifier: Topic :: Software Development
Classifier: Topic :: Software Development :: Libraries :: Application Frameworks
Requires-Python: >=3.7
License-File: LICENSE.txt
Requires-Dist: django-cms (>=3.11)
Requires-Dist: django-parler (>=1.9.2)
Requires-Dist: python-slugify (>=1.2.6)
